setup.py
CityMaker_SDK.egg-info/PKG-INFO
CityMaker_SDK.egg-info/SOURCES.txt
CityMaker_SDK.egg-info/dependency_links.txt
CityMaker_SDK.egg-info/requires.txt
CityMaker_SDK.egg-info/top_level.txt
citymaker_sdk/AsyncDemo.py
citymaker_sdk/CityMaker_Enum.py
citymaker_sdk/GoogleDemo.py
citymaker_sdk/TileHoleDemo.py
citymaker_sdk/TonySDK.py
citymaker_sdk/__init__.py
citymaker_sdk/testDemo.py
citymaker_sdk/tkinterDemo.py
citymaker_sdk.egg-info/PKG-INFO
citymaker_sdk.egg-info/SOURCES.txt
citymaker_sdk.egg-info/dependency_links.txt
citymaker_sdk.egg-info/requires.txt
citymaker_sdk.egg-info/top_level.txt
citymaker_sdk/CityMaker_PySDK/__init__.py
citymaker_sdk/CityMaker_PySDK/SDK_json/__init__.py
citymaker_sdk/SDK/__init__.py
citymaker_sdk/SDK/Common/IBinaryBuffer.py
citymaker_sdk/SDK/Common/ICoordSysDialog.py
citymaker_sdk/SDK/Common/IDoubleArray.py
citymaker_sdk/SDK/Common/IFloatArray.py
citymaker_sdk/SDK/Common/ILicenseServer.py
citymaker_sdk/SDK/Common/IPropertySet.py
citymaker_sdk/SDK/Common/IRuntimeInfo.py
citymaker_sdk/SDK/Common/IUInt16Array.py
citymaker_sdk/SDK/Common/IUInt32Array.py
citymaker_sdk/SDK/Common/__init__.py
citymaker_sdk/SDK/Common/index.py
citymaker_sdk/SDK/FdeCore/FeatureDataSet.py
citymaker_sdk/SDK/FdeCore/IAttachment.py
citymaker_sdk/SDK/FdeCore/IAttachmentCollection.py
citymaker_sdk/SDK/FdeCore/IAttachmentManager.py
citymaker_sdk/SDK/FdeCore/ICheckIn.py
citymaker_sdk/SDK/FdeCore/ICheckOut.py
citymaker_sdk/SDK/FdeCore/ICodedValueDomain.py
citymaker_sdk/SDK/FdeCore/IConflict.py
citymaker_sdk/SDK/FdeCore/IConnectionInfo.py
citymaker_sdk/SDK/FdeCore/IDataSource.py
citymaker_sdk/SDK/FdeCore/IDataSourceFactory.py
citymaker_sdk/SDK/FdeCore/IDataSourcePluginManager.py
citymaker_sdk/SDK/FdeCore/IDbIndexInfo.py
citymaker_sdk/SDK/FdeCore/IDbIndexInfoCollection.py
citymaker_sdk/SDK/FdeCore/IDomain.py
citymaker_sdk/SDK/FdeCore/IDomainFactory.py
citymaker_sdk/SDK/FdeCore/IEnumResName.py
citymaker_sdk/SDK/FdeCore/IFdeCursor.py
citymaker_sdk/SDK/FdeCore/IFeatureClass.py
citymaker_sdk/SDK/FdeCore/IFeatureClassQuery.py
citymaker_sdk/SDK/FdeCore/IFeatureDataSet.py
citymaker_sdk/SDK/FdeCore/IFeatureProgress.py
citymaker_sdk/SDK/FdeCore/IFieldDomainInfo.py
citymaker_sdk/SDK/FdeCore/IFieldInfo.py
citymaker_sdk/SDK/FdeCore/IFieldInfoCollection.py
citymaker_sdk/SDK/FdeCore/IGeometryDef.py
citymaker_sdk/SDK/FdeCore/IGridIndexInfo.py
