Metadata-Version: 1.2
Name: citymaker-sdk
Version: 1.1.15.0
Summary: this is CityMaker_SDK for python
Home-page: https://gitee.com/zhoutongit/CityMaker_PySDK
Author: Gvitech
Author-email: zhoutongit@163.com
License: Copyright (c) 2020 The Python Packaging Authority
